LICENSE
di_service_locator/__init__.py
di_service_locator/config.py
di_service_locator/definitions.py
di_service_locator/exceptions.py
di_service_locator/feature_defs/__init__.py
di_service_locator/feature_defs/aws/__init__.py
di_service_locator/feature_defs/aws/blob_storage.py
di_service_locator/feature_defs/blob_storage.py
di_service_locator/feature_defs/gcp/__init__.py
di_service_locator/feature_defs/gcp/blob_storage.py
di_service_locator/feature_defs/instrumentation.py
di_service_locator/feature_defs/interfaces.py
di_service_locator/features.py
di_service_locator/files.py
di_service_locator/instantiator.py
di_service_locator/py.typed
di_service_locator/utils/__init__.py
di_service_locator/utils/helpers.py
di_service_locator/utils/transcoding.py
di_service_locator-1.3.0.dist-info/LICENSE
di_service_locator-1.3.0.dist-info/METADATA
di_service_locator-1.3.0.dist-info/WHEEL
di_service_locator-1.3.0.dist-info/RECORD
