Metadata-Version: 2.1
Name: di-service-locator
Version: 1.3.0
Summary: Injection utilities to obtain instances of dynamically created features from config
Home-page: https://deeperinsights.com
License: MIT
Requires-Python: >=3.9,<4.0
Classifier: License :: OSI Approved :: MIT License
Classifier: Programming Language :: Python :: 3
Classifier: Programming Language :: Python :: 3.9
Classifier: Programming Language :: Python :: 3.10
Classifier: Programming Language :: Python :: 3.11
Classifier: Programming Language :: Python :: 3.12
Provides-Extra: aws
Provides-Extra: gcp
Requires-Dist: boto3 (>=1.20.24,<2.0.0) ; extra == "aws"
Requires-Dist: botocore (>=1.23.24,<2.0.0) ; extra == "aws"
Requires-Dist: di-logging (>=1.0.0,<2.0.0)
Requires-Dist: google-cloud-storage (>=2.5.0,<3.0.0) ; extra == "gcp"
Project-URL: Repository, https://github.com/skimit/di-service-locator
